{
  "tiny_tigers": {
    "video": "https://masterbaez.com/wp-content/uploads/2026/05/Leadpage-Tini-Tiger-Video-.mp4",
    "link": "",
    "checkout": "",
    "imagen": ""
  },
  "kids": {
    "video": "https://masterbaez.com/wp-content/uploads/2026/05/Kids-7-12.mp4",
    "link": "",
    "checkout": "",
    "imagen": ""
  },
  "adults": {
    "video": "https://afterschoolcoopercity.com/wp-content/uploads/2026/05/Adult-Martial-Arts.mp4",
    "link": "",
    "checkout": "",
    "imagen": ""
  },
  "after_school": {
    "video": "https://afterschoolcoopercity.com/wp-content/uploads/2023/10/asp-cooper-city-Loking.mp4",
    "link": "",
    "checkout": "",
    "imagen": ""
  }
}
